CHANGES.rst
MANIFEST.in
Makefile
Makefile.release
README.rst
setup.py
version.txt
src/metapensiero/__init__.py
src/metapensiero.tool.bump_version.egg-info/PKG-INFO
src/metapensiero.tool.bump_version.egg-info/SOURCES.txt
src/metapensiero.tool.bump_version.egg-info/dependency_links.txt
src/metapensiero.tool.bump_version.egg-info/entry_points.txt
src/metapensiero.tool.bump_version.egg-info/namespace_packages.txt
src/metapensiero.tool.bump_version.egg-info/pbr.json
src/metapensiero.tool.bump_version.egg-info/requires.txt
src/metapensiero.tool.bump_version.egg-info/top_level.txt
src/metapensiero/tool/__init__.py
src/metapensiero/tool/bump_version/__init__.py