Metadata-Version: 1.1
Name: metapensiero.tool.bump-version
Version: 1.1
Summary: A simple tool to bump version number of a Python package
Home-page: https://bitbucket.org/lele/metapensiero.tool.bump_version
Author: Lele Gaifax
Author-email: lele@metapensiero.it
License: GPLv3+
Platform: UNKNOWN
Classifier: Development Status :: 5 - Production/Stable
Classifier: Intended Audience :: Developers
Classifier: Programming Language :: Python
Classifier: Programming Language :: Python :: 2
Classifier: Programming Language :: Python :: 2.7
Classifier: Programming Language :: Python :: 3
Classifier: Programming Language :: Python :: 3.4
